Workbook

Sheet Project Instructions
A1: PR. 2 Analyzer
A2: Topics: - Conditional Formatting - WHAT IF Analysis - Linear Regression (Using Data Analysis Toolpak) - Data Analysis Feature (Descriptive Stats, Regression, Histogram) - Data Storytelling - Add Symbols or Arrows in Custom Formatting - Create Timestamp - Find High-Value Customers using Groupby(), index(), and match() combination - Advanced Descriptive Analytics - Pivot Table with Dashboard - Creating bar charts - Creating line charts - Creating pie charts Main Tasks: 1. Apply conditional formatting to highlight top 10 customers based on total purchase. 2. Perform WHAT IF Analysis to see impact of changing discount on total profit. 3. Use Data Analysis Toolpak to run Linear Regression (Profit vs Sales). 4. Use 'Descriptive Statistics' from Analysis Toolpak on the dataset. 5. Add up/down arrows on monthly sales growth. 6. Create a timestamp column using NOW(). 7. Identify high-value customers using index(), match(), and filters. 8. Create Pivot Table to analyze total sales by region and product. 9. Create bar, line, and pie charts to visualize KPIs. 10. Summarize insights using a dashboard. Deliverable: Complete the given worksheet by applying the required formulas in respective sheets.

Sheet Dataset
A1: Customer_ID | B1: Customer_Name | C1: Region | D1: Product_Category | E1: Sales | F1: Quantity | G1: Discount | H1: Order_Date | I1: Profit | J1: Timestamp
A2: CUST019 | B2: James Davis | C2: West | D2: Books | E2: 1036.09 | F2: 4 | G2: 0.2 | H2: 45392 | I2: 331.55 | J2: =NOW() -> 46303.651
A3: CUST012 | B3: Robert Anderson | C3: West | D3: Clothing | E3: 1101.28 | F3: 3 | G3: 0.2 | H3: 45393 | I3: 440.51 | J3: =NOW() -> 46303.651
A4: CUST017 | B4: James Taylor | C4: East | D4: Books | E4: 713.34 | F4: 17 | G4: 0 | H4: 45396 | I4: 285.34 | J4: =NOW() -> 46303.651
A5: CUST005 | B5: Robert Anderson | C5: South | D5: Electronics | E5: 760.93 | F5: 4 | G5: 0.15 | H5: 45396 | I5: 161.7 | J5: =NOW() -> 46303.651
A6: CUST030 | B6: James Wilson | C6: North | D6: Books | E6: 847 | F6: 12 | G6: 0.2 | H6: 45397 | I6: 271.04 | J6: =NOW() -> 46303.651
A7: CUST007 | B7: Michael Anderson | C7: North | D7: Furniture | E7: 965.64 | F7: 8 | G7: 0.1 | H7: 45398 | I7: 304.18 | J7: =NOW() -> 46303.651
A8: CUST001 | B8: Linda Wilson | C8: West | D8: Electronics | E8: 1317.53 | F8: 12 | G8: 0.05 | H8: 45398 | I8: 312.91 | J8: =NOW() -> 46303.651
A9: CUST026 | B9: Mary Davis | C9: East | D9: Furniture | E9: 1074.47 | F9: 6 | G9: 0.2 | H9: 45401 | I9: 300.85 | J9: =NOW() -> 46303.651
A10: CUST009 | B10: Linda Jackson | C10: Central | D10: Books | E10: 501.54 | F10: 11 | G10: 0.05 | H10: 45401 | I10: 190.59 | J10: =NOW() -> 46303.651
A11: CUST010 | B11: David Thomas | C11: Central | D11: Clothing | E11: 737.31 | F11: 2 | G11: 0.05 | H11: 45401 | I11: 350.22 | J11: =NOW() -> 46303.651
A12: CUST014 | B12: Emma Davis | C12: West | D12: Office Supplies | E12: 1572.82 | F12: 6 | G12: 0.05 | H12: 45402 | I12: 672.38 | J12: =NOW() -> 46303.651
A13: CUST014 | B13: David Thomas | C13: Central | D13: Books | E13: 1343.13 | F13: 14 | G13: 0.15 | H13: 45404 | I13: 456.66 | J13: =NOW() -> 46303.651
... A201: CUST016 | B201: David Thomas | C201: South | D201: Clothing | E201: 928.32 | F201: 2 | G201: 0.05 | H201: 45754 | I201: 440.95 | J201: =NOW() -> 46303.651

Sheet Top 10 Customers
A1: Task 1 – Top 10 Customers by Total Purchase (Conditional Formatting)
A3: Customer_ID | B3: Total Purchase (₹) | C3: Rank | E3: Highlight rule: green = top 10 customers by total purchase (Top 10 rule on column B).
A4: CUST001 | B4: =SUMIF(Dataset!$A$2:$A$201,A4,Dataset!$E$2:$E$201) -> 6549.55 | C4: =RANK(B4,$B$4:$B$33) -> 15
A5: CUST002 | B5: =SUMIF(Dataset!$A$2:$A$201,A5,Dataset!$E$2:$E$201) -> 6481.43 | C5: =RANK(B5,$B$4:$B$33) -> 17
A6: CUST003 | B6: =SUMIF(Dataset!$A$2:$A$201,A6,Dataset!$E$2:$E$201) -> 8490.18 | C6: =RANK(B6,$B$4:$B$33) -> 7
A7: CUST004 | B7: =SUMIF(Dataset!$A$2:$A$201,A7,Dataset!$E$2:$E$201) -> 7813.59 | C7: =RANK(B7,$B$4:$B$33) -> 10
A8: CUST005 | B8: =SUMIF(Dataset!$A$2:$A$201,A8,Dataset!$E$2:$E$201) -> 6666.13 | C8: =RANK(B8,$B$4:$B$33) -> 14
A9: CUST006 | B9: =SUMIF(Dataset!$A$2:$A$201,A9,Dataset!$E$2:$E$201) -> 2699.75 | C9: =RANK(B9,$B$4:$B$33) -> 30
A10: CUST007 | B10: =SUMIF(Dataset!$A$2:$A$201,A10,Dataset!$E$2:$E$201) -> 9941.88 | C10: =RANK(B10,$B$4:$B$33) -> 3
A11: CUST008 | B11: =SUMIF(Dataset!$A$2:$A$201,A11,Dataset!$E$2:$E$201) -> 9760.8 | C11: =RANK(B11,$B$4:$B$33) -> 4
A12: CUST009 | B12: =SUMIF(Dataset!$A$2:$A$201,A12,Dataset!$E$2:$E$201) -> 6505.2 | C12: =RANK(B12,$B$4:$B$33) -> 16
A13: CUST010 | B13: =SUMIF(Dataset!$A$2:$A$201,A13,Dataset!$E$2:$E$201) -> 4259.22 | C13: =RANK(B13,$B$4:$B$33) -> 24
A14: CUST011 | B14: =SUMIF(Dataset!$A$2:$A$201,A14,Dataset!$E$2:$E$201) -> 3762.29 | C14: =RANK(B14,$B$4:$B$33) -> 27
A15: CUST012 | B15: =SUMIF(Dataset!$A$2:$A$201,A15,Dataset!$E$2:$E$201) -> 8339 | C15: =RANK(B15,$B$4:$B$33) -> 8
... A33: CUST030 | B33: =SUMIF(Dataset!$A$2:$A$201,A33,Dataset!$E$2:$E$201) -> 7928.71 | C33: =RANK(B33,$B$4:$B$33) -> 9

Sheet What-If Analysis
A1: Task 2 – What-If Analysis: Impact of Discount on Total Profit
A3: Total Sales (actual) | B3: =SUM(Dataset!$E$2:$E$201) -> 195217.76
A4: Total Profit (actual) | B4: =SUM(Dataset!$I$2:$I$201) -> 68287.01
A5: Average Discount (actual) | B5: =AVERAGE(Dataset!$G$2:$G$201) -> 0.09725
A6: Total List Price (sales before discount) | B6: =SUMPRODUCT(Dataset!$E$2:$E$201/(1-Dataset!$G$2:$G$201)) -> 218027.19
A8: Scenario: New Discount Rate (change me) | B8: 0.1
A9: Scenario Total Sales | B9: =B6*(1-B8) -> 196224.47
A10: Scenario Total Profit | B10: =B4+(B9-B3) -> 69293.725
A11: Change in Profit (₹) | B11: =B10-B4 -> 1006.7146
A12: Change in Profit (%) | B12: =B11/B4 -> 0.014742402
A14: Discount Sensitivity (what-if table)
A15: Discount Rate | B15: Total Sales (₹) | C15: Total Profit (₹) | D15: Change in Profit (₹) | E15: Change in Profit (%) | F15: Profit Margin
A16: 0 | B16: =$B$6*(1-A16) -> 218027.19 | C16: =$B$4+(B16-$B$3) -> 91096.444 | D16: =C16-$B$4 -> 22809.434 | E16: =D16/$B$4 -> 0.33402303 | F16: =C16/B16 -> 0.41782148
A17: 0.05 | B17: =$B$6*(1-A17) -> 207125.83 | C17: =$B$4+(B17-$B$3) -> 80195.084 | D17: =C17-$B$4 -> 11908.074 | E17: =D17/$B$4 -> 0.17438272 | F17: =C17/B17 -> 0.3871805
A18: 0.1 | B18: =$B$6*(1-A18) -> 196224.47 | C18: =$B$4+(B18-$B$3) -> 69293.725 | D18: =C18-$B$4 -> 1006.7146 | E18: =D18/$B$4 -> 0.014742402 | F18: =C18/B18 -> 0.35313497
A19: 0.15 | B19: =$B$6*(1-A19) -> 185323.11 | C19: =$B$4+(B19-$B$3) -> 58392.365 | D19: =C19-$B$4 -> -9894.6451 | E19: =D19/$B$4 -> -0.14489791 | F19: =C19/B19 -> 0.31508409
A20: 0.2 | B20: =$B$6*(1-A20) -> 174421.76 | C20: =$B$4+(B20-$B$3) -> 47491.005 | D20: =C20-$B$4 -> -20796.005 | E20: =D20/$B$4 -> -0.30453823 | F20: =C20/B20 -> 0.27227684
A21: 0.25 | B21: =$B$6*(1-A21) -> 163520.4 | C21: =$B$4+(B21-$B$3) -> 36589.645 | D21: =C21-$B$4 -> -31697.365 | E21: =D21/$B$4 -> -0.46417854 | F21: =C21/B21 -> 0.22376197
A23: Assumptions: Sales in the dataset are net of each order's discount, so list price = Sales/(1–Discount). A new discount rate re-prices every order from list price; costs and quantities are held constant, so the entire change in revenue flows through to profit. Blue cells are inputs.

Sheet Regression
A1: Task 3 – Linear Regression: Profit (Y) vs Sales (X) [Analysis ToolPak layout, live formulas]
A3: SUMMARY OUTPUT
A4: Regression Statistics
A5: Multiple R | B5: =SQRT(RSQ(Dataset!$I$2:$I$201,Dataset!$E$2:$E$201)) -> 0.77340306
A6: R Square | B6: =RSQ(Dataset!$I$2:$I$201,Dataset!$E$2:$E$201) -> 0.5981523
A7: Adjusted R Square | B7: =1-(1-B6)*(B9-1)/(B9-2) -> 0.59612277
A8: Standard Error | B8: =STEYX(Dataset!$I$2:$I$201,Dataset!$E$2:$E$201) -> 86.281231
A9: Observations | B9: =COUNT(Dataset!$E$2:$E$201) -> 200
A11: ANOVA
B12: df | C12: SS | D12: MS | E12: F | F12: Significance F
A13: Regression | B13: 1 | C13: =INDEX(LINEST(Dataset!$I$2:$I$201,Dataset!$E$2:$E$201,TRUE(),TRUE()),5,1) -> 2194058.2 | D13: =C13/B13 -> 2194058.2 | E13: =D13/D14 -> 294.72398 | F13: =FDIST(E13,B13,B14) -> 4.6269368e-41
A14: Residual | B14: =B9-2 -> 198 | C14: =INDEX(LINEST(Dataset!$I$2:$I$201,Dataset!$E$2:$E$201,TRUE(),TRUE()),5,2) -> 1474001.2 | D14: =C14/B14 -> 7444.4507
A15: Total | B15: =B9-1 -> 199 | C15: =C13+C14 -> 3668059.4
B17: Coefficients | C17: Standard Error | D17: t Stat | E17: P-value | F17: Lower 95% | G17: Upper 95%
A18: Intercept | B18: =INTERCEPT(Dataset!$I$2:$I$201,Dataset!$E$2:$E$201) -> -1.0315505 | C18: =INDEX(LINEST(Dataset!$I$2:$I$201,Dataset!$E$2:$E$201,TRUE(),TRUE()),2,2) -> 20.860617 | D18: =B18/C18 -> -0.049449663 | E18: =TDIST(ABS(D18),$B$14,2) -> 0.9606108 | F18: =B18-TINV(0.05,$B$14)*C18 -> -42.169052 | G18: =B18+TINV(0.05,$B$14)*C18 -> 40.105951
A19: Sales (X) | B19: =SLOPE(Dataset!$I$2:$I$201,Dataset!$E$2:$E$201) -> 0.35085599 | C19: =INDEX(LINEST(Dataset!$I$2:$I$201,Dataset!$E$2:$E$201,TRUE(),TRUE()),2,1) -> 0.020437189 | D19: =B19/C19 -> 17.167527 | E19: =TDIST(ABS(D19),$B$14,2) -> 4.6269368e-41 | F19: =B19-TINV(0.05,$B$14)*C19 -> 0.3105535 | G19: =B19+TINV(0.05,$B$14)*C19 -> 0.39115848
A21: Fitted equation: | B21: ="Profit = "&TEXT(B18,"0.00")&" + "&TEXT(B19,"0.0000")&" × Sales" -> Profit = -1.03 + 0.3509 × Sales
A22: Interpretation: | B22: ="Each extra ₹1 of sales is associated with ₹"&TEXT(B19,"0.000")&" more profit; Sales explains "&TEXT(B6,"0.0%")&" of the variation in Profit." -> Each extra ₹1 of sales is associated with ₹0.351 more profit; Sales explains 59.8% of the variation in Profit.

Sheet Descriptive Stats
A1: Task 4 – Descriptive Statistics (Analysis ToolPak layout, live formulas)
A3: Statistic | B3: Sales | C3: Quantity | D3: Discount | E3: Profit
A4: Mean | B4: =AVERAGE(Dataset!$E$2:$E$201) -> 976.0888 | C4: =AVERAGE(Dataset!$F$2:$F$201) -> 9.995 | D4: =AVERAGE(Dataset!$G$2:$G$201) -> 0.09725 | E4: =AVERAGE(Dataset!$I$2:$I$201) -> 341.43505
A5: Standard Error | B5: =STDEV(Dataset!$E$2:$E$201)/SQRT(COUNT(Dataset!$E$2:$E$201)) -> 21.16185 | C5: =STDEV(Dataset!$F$2:$F$201)/SQRT(COUNT(Dataset!$F$2:$F$201)) -> 0.39927683 | D5: =STDEV(Dataset!$G$2:$G$201)/SQRT(COUNT(Dataset!$G$2:$G$201)) -> 0.0051142414 | E5: =STDEV(Dataset!$I$2:$I$201)/SQRT(COUNT(Dataset!$I$2:$I$201)) -> 9.6001196
A6: Median | B6: =MEDIAN(Dataset!$E$2:$E$201) -> 976.72 | C6: =MEDIAN(Dataset!$F$2:$F$201) -> 10 | D6: =MEDIAN(Dataset!$G$2:$G$201) -> 0.1 | E6: =MEDIAN(Dataset!$I$2:$I$201) -> 332.255
A7: Mode | B7: =IFERROR(MODE(Dataset!$E$2:$E$201),"N/A") -> N/A | C7: =IFERROR(MODE(Dataset!$F$2:$F$201),"N/A") -> 8 | D7: =IFERROR(MODE(Dataset!$G$2:$G$201),"N/A") -> 0 | E7: =IFERROR(MODE(Dataset!$I$2:$I$201),"N/A") -> N/A
A8: Standard Deviation | B8: =STDEV(Dataset!$E$2:$E$201) -> 299.27376 | C8: =STDEV(Dataset!$F$2:$F$201) -> 5.646627 | D8: =STDEV(Dataset!$G$2:$G$201) -> 0.072326295 | E8: =STDEV(Dataset!$I$2:$I$201) -> 135.76619
A9: Sample Variance | B9: =VAR(Dataset!$E$2:$E$201) -> 89564.783 | C9: =VAR(Dataset!$F$2:$F$201) -> 31.884397 | D9: =VAR(Dataset!$G$2:$G$201) -> 0.005231093 | E9: =VAR(Dataset!$I$2:$I$201) -> 18432.459
A10: Kurtosis | B10: =KURT(Dataset!$E$2:$E$201) -> -0.088595232 | C10: =KURT(Dataset!$F$2:$F$201) -> -1.2091054 | D10: =KURT(Dataset!$G$2:$G$201) -> -1.3257012 | E10: =KURT(Dataset!$I$2:$I$201) -> 0.26450644
A11: Skewness | B11: =SKEW(Dataset!$E$2:$E$201) -> 0.14685797 | C11: =SKEW(Dataset!$F$2:$F$201) -> 0.060845864 | D11: =SKEW(Dataset!$G$2:$G$201) -> 0.096827386 | E11: =SKEW(Dataset!$I$2:$I$201) -> 0.57339636
A12: Range | B12: =MAX(Dataset!$E$2:$E$201)-MIN(Dataset!$E$2:$E$201) -> 1665.15 | C12: =MAX(Dataset!$F$2:$F$201)-MIN(Dataset!$F$2:$F$201) -> 18 | D12: =MAX(Dataset!$G$2:$G$201)-MIN(Dataset!$G$2:$G$201) -> 0.2 | E12: =MAX(Dataset!$I$2:$I$201)-MIN(Dataset!$I$2:$I$201) -> 704.83
A13: Minimum | B13: =MIN(Dataset!$E$2:$E$201) -> 258.51 | C13: =MIN(Dataset!$F$2:$F$201) -> 1 | D13: =MIN(Dataset!$G$2:$G$201) -> 0 | E13: =MIN(Dataset!$I$2:$I$201) -> 64.63
A14: Maximum | B14: =MAX(Dataset!$E$2:$E$201) -> 1923.66 | C14: =MAX(Dataset!$F$2:$F$201) -> 19 | D14: =MAX(Dataset!$G$2:$G$201) -> 0.2 | E14: =MAX(Dataset!$I$2:$I$201) -> 769.46
A15: Sum | B15: =SUM(Dataset!$E$2:$E$201) -> 195217.76 | C15: =SUM(Dataset!$F$2:$F$201) -> 1999 | D15: =SUM(Dataset!$G$2:$G$201) -> 19.45 | E15: =SUM(Dataset!$I$2:$I$201) -> 68287.01
A16: Count | B16: =COUNT(Dataset!$E$2:$E$201) -> 200 | C16: =COUNT(Dataset!$F$2:$F$201) -> 200 | D16: =COUNT(Dataset!$G$2:$G$201) -> 200 | E16: =COUNT(Dataset!$I$2:$I$201) -> 200
A17: Largest(1) | B17: =LARGE(Dataset!$E$2:$E$201,1) -> 1923.66 | C17: =LARGE(Dataset!$F$2:$F$201,1) -> 19 | D17: =LARGE(Dataset!$G$2:$G$201,1) -> 0.2 | E17: =LARGE(Dataset!$I$2:$I$201,1) -> 769.46
A18: Smallest(1) | B18: =SMALL(Dataset!$E$2:$E$201,1) -> 258.51 | C18: =SMALL(Dataset!$F$2:$F$201,1) -> 1 | D18: =SMALL(Dataset!$G$2:$G$201,1) -> 0 | E18: =SMALL(Dataset!$I$2:$I$201,1) -> 64.63
A19: Confidence Level(95.0%) | B19: =TINV(0.05,COUNT(Dataset!$E$2:$E$201)-1)*STDEV(Dataset!$E$2:$E$201)/SQRT(COUNT(Dataset!$E$2:$E$201)) -> 41.730249 | C19: =TINV(0.05,COUNT(Dataset!$F$2:$F$201)-1)*STDEV(Dataset!$F$2:$F$201)/SQRT(COUNT(Dataset!$F$2:$F$201)) -> 0.78735655 | D19: =TINV(0.05,COUNT(Dataset!$G$2:$G$201)-1)*STDEV(Dataset!$G$2:$G$201)/SQRT(COUNT(Dataset!$G$2:$G$201)) -> 0.010085062 | E19: =TINV(0.05,COUNT(Dataset!$I$2:$I$201)-1)*STDEV(Dataset!$I$2:$I$201)/SQRT(COUNT(Dataset!$I$2:$I$201)) -> 18.931019
A21: Mode shows N/A when no value repeats.

Sheet Sales Growth
A1: Task 5 – Monthly Sales Growth with Up/Down Arrows (custom number format)
A3: Month | B3: Total Sales (₹) | C3: MoM Growth %
A4: =DATE(YEAR(MIN(Dataset!$H$2:$H$201)),MONTH(MIN(Dataset!$H$2:$H$201)),1) -> 45383 | B4: =SUMIFS(Dataset!$E$2:$E$201,Dataset!$H$2:$H$201,">="&A4,Dataset!$H$2:$H$201,"<"&EDATE(A4,1)) -> 19029.96 | C4: n/a
A5: =EDATE(A4,1) -> 45413 | B5: =SUMIFS(Dataset!$E$2:$E$201,Dataset!$H$2:$H$201,">="&A5,Dataset!$H$2:$H$201,"<"&EDATE(A5,1)) -> 18507.34 | C5: =IF(B4=0,0,(B5-B4)/B4) -> -0.027463011
A6: =EDATE(A5,1) -> 45444 | B6: =SUMIFS(Dataset!$E$2:$E$201,Dataset!$H$2:$H$201,">="&A6,Dataset!$H$2:$H$201,"<"&EDATE(A6,1)) -> 20187.51 | C6: =IF(B5=0,0,(B6-B5)/B5) -> 0.090783981
A7: =EDATE(A6,1) -> 45474 | B7: =SUMIFS(Dataset!$E$2:$E$201,Dataset!$H$2:$H$201,">="&A7,Dataset!$H$2:$H$201,"<"&EDATE(A7,1)) -> 11609.04 | C7: =IF(B6=0,0,(B7-B6)/B6) -> -0.42493948
A8: =EDATE(A7,1) -> 45505 | B8: =SUMIFS(Dataset!$E$2:$E$201,Dataset!$H$2:$H$201,">="&A8,Dataset!$H$2:$H$201,"<"&EDATE(A8,1)) -> 10091.7 | C8: =IF(B7=0,0,(B8-B7)/B7) -> -0.13070331
A9: =EDATE(A8,1) -> 45536 | B9: =SUMIFS(Dataset!$E$2:$E$201,Dataset!$H$2:$H$201,">="&A9,Dataset!$H$2:$H$201,"<"&EDATE(A9,1)) -> 20533.5 | C9: =IF(B8=0,0,(B9-B8)/B8) -> 1.0346919
A10: =EDATE(A9,1) -> 45566 | B10: =SUMIFS(Dataset!$E$2:$E$201,Dataset!$H$2:$H$201,">="&A10,Dataset!$H$2:$H$201,"<"&EDATE(A10,1)) -> 14215.24 | C10: =IF(B9=0,0,(B10-B9)/B9) -> -0.30770497
A11: =EDATE(A10,1) -> 45597 | B11: =SUMIFS(Dataset!$E$2:$E$201,Dataset!$H$2:$H$201,">="&A11,Dataset!$H$2:$H$201,"<"&EDATE(A11,1)) -> 20135.03 | C11: =IF(B10=0,0,(B11-B10)/B10) -> 0.41643968
A12: =EDATE(A11,1) -> 45627 | B12: =SUMIFS(Dataset!$E$2:$E$201,Dataset!$H$2:$H$201,">="&A12,Dataset!$H$2:$H$201,"<"&EDATE(A12,1)) -> 11120.04 | C12: =IF(B11=0,0,(B12-B11)/B11) -> -0.44772667
A13: =EDATE(A12,1) -> 45658 | B13: =SUMIFS(Dataset!$E$2:$E$201,Dataset!$H$2:$H$201,">="&A13,Dataset!$H$2:$H$201,"<"&EDATE(A13,1)) -> 14914.65 | C13: =IF(B12=0,0,(B13-B12)/B12) -> 0.34124068
A14: =EDATE(A13,1) -> 45689 | B14: =SUMIFS(Dataset!$E$2:$E$201,Dataset!$H$2:$H$201,">="&A14,Dataset!$H$2:$H$201,"<"&EDATE(A14,1)) -> 14006.36 | C14: =IF(B13=0,0,(B14-B13)/B13) -> -0.060899183
A15: =EDATE(A14,1) -> 45717 | B15: =SUMIFS(Dataset!$E$2:$E$201,Dataset!$H$2:$H$201,">="&A15,Dataset!$H$2:$H$201,"<"&EDATE(A15,1)) -> 17655.22 | C15: =IF(B14=0,0,(B15-B14)/B14) -> 0.26051451
A16: =EDATE(A15,1) -> 45748 | B16: =SUMIFS(Dataset!$E$2:$E$201,Dataset!$H$2:$H$201,">="&A16,Dataset!$H$2:$H$201,"<"&EDATE(A16,1)) -> 3212.17 | C16: =IF(B15=0,0,(B16-B15)/B15) -> -0.81806117
A18: Total | B18: =SUM(B4:B16) -> 195217.76 | C18: =IF(B18=SUM(Dataset!$E$2:$E$201),"✔ ties to Dataset","check") -> ✔ ties to Dataset

Sheet High-Value Customers
A1: Task 7 – High-Value Customers (LARGE + INDEX + MATCH, with filters)
A3: High-value threshold (avg customer total, ₹) | D3: =AVERAGE('Top 10 Customers'!$B$4:$B$33) -> 6507.2587
A5: Rank | B5: Customer_ID | C5: Total Purchase (₹) | D5: Total Profit (₹) | E5: No. of Orders | F5: Segment | H5: Use the filter arrows on row 5 (e.g. Segment = High-Value) to list high-value customers.
A6: 1 | B6: =INDEX('Top 10 Customers'!$A$4:$A$33,MATCH(C6,'Top 10 Customers'!$B$4:$B$33,0)) -> CUST015 | C6: =LARGE('Top 10 Customers'!$B$4:$B$33,A6) -> 11611.06 | D6: =SUMIF(Dataset!$A$2:$A$201,B6,Dataset!$I$2:$I$201) -> 4201.59 | E6: =COUNTIF(Dataset!$A$2:$A$201,B6) -> 11 | F6: =IF(C6>=$D$3,"High-Value","Standard") -> High-Value
A7: 2 | B7: =INDEX('Top 10 Customers'!$A$4:$A$33,MATCH(C7,'Top 10 Customers'!$B$4:$B$33,0)) -> CUST028 | C7: =LARGE('Top 10 Customers'!$B$4:$B$33,A7) -> 10293.87 | D7: =SUMIF(Dataset!$A$2:$A$201,B7,Dataset!$I$2:$I$201) -> 3541.02 | E7: =COUNTIF(Dataset!$A$2:$A$201,B7) -> 12 | F7: =IF(C7>=$D$3,"High-Value","Standard") -> High-Value
A8: 3 | B8: =INDEX('Top 10 Customers'!$A$4:$A$33,MATCH(C8,'Top 10 Customers'!$B$4:$B$33,0)) -> CUST007 | C8: =LARGE('Top 10 Customers'!$B$4:$B$33,A8) -> 9941.88 | D8: =SUMIF(Dataset!$A$2:$A$201,B8,Dataset!$I$2:$I$201) -> 3936.26 | E8: =COUNTIF(Dataset!$A$2:$A$201,B8) -> 10 | F8: =IF(C8>=$D$3,"High-Value","Standard") -> High-Value
A9: 4 | B9: =INDEX('Top 10 Customers'!$A$4:$A$33,MATCH(C9,'Top 10 Customers'!$B$4:$B$33,0)) -> CUST008 | C9: =LARGE('Top 10 Customers'!$B$4:$B$33,A9) -> 9760.8 | D9: =SUMIF(Dataset!$A$2:$A$201,B9,Dataset!$I$2:$I$201) -> 3442.48 | E9: =COUNTIF(Dataset!$A$2:$A$201,B9) -> 10 | F9: =IF(C9>=$D$3,"High-Value","Standard") -> High-Value
A10: 5 | B10: =INDEX('Top 10 Customers'!$A$4:$A$33,MATCH(C10,'Top 10 Customers'!$B$4:$B$33,0)) -> CUST026 | C10: =LARGE('Top 10 Customers'!$B$4:$B$33,A10) -> 9371.81 | D10: =SUMIF(Dataset!$A$2:$A$201,B10,Dataset!$I$2:$I$201) -> 2922.02 | E10: =COUNTIF(Dataset!$A$2:$A$201,B10) -> 9 | F10: =IF(C10>=$D$3,"High-Value","Standard") -> High-Value
A11: 6 | B11: =INDEX('Top 10 Customers'!$A$4:$A$33,MATCH(C11,'Top 10 Customers'!$B$4:$B$33,0)) -> CUST021 | C11: =LARGE('Top 10 Customers'!$B$4:$B$33,A11) -> 8740.18 | D11: =SUMIF(Dataset!$A$2:$A$201,B11,Dataset!$I$2:$I$201) -> 2848.62 | E11: =COUNTIF(Dataset!$A$2:$A$201,B11) -> 8 | F11: =IF(C11>=$D$3,"High-Value","Standard") -> High-Value
A12: 7 | B12: =INDEX('Top 10 Customers'!$A$4:$A$33,MATCH(C12,'Top 10 Customers'!$B$4:$B$33,0)) -> CUST003 | C12: =LARGE('Top 10 Customers'!$B$4:$B$33,A12) -> 8490.18 | D12: =SUMIF(Dataset!$A$2:$A$201,B12,Dataset!$I$2:$I$201) -> 2652.75 | E12: =COUNTIF(Dataset!$A$2:$A$201,B12) -> 9 | F12: =IF(C12>=$D$3,"High-Value","Standard") -> High-Value
A13: 8 | B13: =INDEX('Top 10 Customers'!$A$4:$A$33,MATCH(C13,'Top 10 Customers'!$B$4:$B$33,0)) -> CUST012 | C13: =LARGE('Top 10 Customers'!$B$4:$B$33,A13) -> 8339 | D13: =SUMIF(Dataset!$A$2:$A$201,B13,Dataset!$I$2:$I$201) -> 2988.71 | E13: =COUNTIF(Dataset!$A$2:$A$201,B13) -> 9 | F13: =IF(C13>=$D$3,"High-Value","Standard") -> High-Value
A14: 9 | B14: =INDEX('Top 10 Customers'!$A$4:$A$33,MATCH(C14,'Top 10 Customers'!$B$4:$B$33,0)) -> CUST030 | C14: =LARGE('Top 10 Customers'!$B$4:$B$33,A14) -> 7928.71 | D14: =SUMIF(Dataset!$A$2:$A$201,B14,Dataset!$I$2:$I$201) -> 2965.48 | E14: =COUNTIF(Dataset!$A$2:$A$201,B14) -> 9 | F14: =IF(C14>=$D$3,"High-Value","Standard") -> High-Value
A15: 10 | B15: =INDEX('Top 10 Customers'!$A$4:$A$33,MATCH(C15,'Top 10 Customers'!$B$4:$B$33,0)) -> CUST004 | C15: =LARGE('Top 10 Customers'!$B$4:$B$33,A15) -> 7813.59 | D15: =SUMIF(Dataset!$A$2:$A$201,B15,Dataset!$I$2:$I$201) -> 3211.82 | E15: =COUNTIF(Dataset!$A$2:$A$201,B15) -> 7 | F15: =IF(C15>=$D$3,"High-Value","Standard") -> High-Value
A16: 11 | B16: =INDEX('Top 10 Customers'!$A$4:$A$33,MATCH(C16,'Top 10 Customers'!$B$4:$B$33,0)) -> CUST024 | C16: =LARGE('Top 10 Customers'!$B$4:$B$33,A16) -> 7583.13 | D16: =SUMIF(Dataset!$A$2:$A$201,B16,Dataset!$I$2:$I$201) -> 2492.1 | E16: =COUNTIF(Dataset!$A$2:$A$201,B16) -> 7 | F16: =IF(C16>=$D$3,"High-Value","Standard") -> High-Value
A17: 12 | B17: =INDEX('Top 10 Customers'!$A$4:$A$33,MATCH(C17,'Top 10 Customers'!$B$4:$B$33,0)) -> CUST014 | C17: =LARGE('Top 10 Customers'!$B$4:$B$33,A17) -> 6729.89 | D17: =SUMIF(Dataset!$A$2:$A$201,B17,Dataset!$I$2:$I$201) -> 2507.18 | E17: =COUNTIF(Dataset!$A$2:$A$201,B17) -> 6 | F17: =IF(C17>=$D$3,"High-Value","Standard") -> High-Value
... A35: 30 | B35: =INDEX('Top 10 Customers'!$A$4:$A$33,MATCH(C35,'Top 10 Customers'!$B$4:$B$33,0)) -> CUST006 | C35: =LARGE('Top 10 Customers'!$B$4:$B$33,A35) -> 2699.75 | D35: =SUMIF(Dataset!$A$2:$A$201,B35,Dataset!$I$2:$I$201) -> 837.06 | E35: =COUNTIF(Dataset!$A$2:$A$201,B35) -> 2 | F35: =IF(C35>=$D$3,"High-Value","Standard") -> Standard
A37: Check: customers ranked | C37: =IF(SUM(C6:C35)=SUM(Dataset!$E$2:$E$201),"✔ ties to total sales","check for tied totals") -> ✔ ties to total sales

Sheet Pivot Table
A1: Task 8 – Total Sales by Region and Product Category
A3: Sum of Sales (₹)
A4: Region | B4: Books | C4: Clothing | D4: Electronics | E4: Furniture | F4: Office Supplies | G4: Grand Total
A5: Central | B5: =SUMIFS(Dataset!$E$2:$E$201,Dataset!$C$2:$C$201,$A5,Dataset!$D$2:$D$201,B$4) -> 11297.15 | C5: =SUMIFS(Dataset!$E$2:$E$201,Dataset!$C$2:$C$201,$A5,Dataset!$D$2:$D$201,C$4) -> 12200.26 | D5: =SUMIFS(Dataset!$E$2:$E$201,Dataset!$C$2:$C$201,$A5,Dataset!$D$2:$D$201,D$4) -> 6621.24 | E5: =SUMIFS(Dataset!$E$2:$E$201,Dataset!$C$2:$C$201,$A5,Dataset!$D$2:$D$201,E$4) -> 4876.96 | F5: =SUMIFS(Dataset!$E$2:$E$201,Dataset!$C$2:$C$201,$A5,Dataset!$D$2:$D$201,F$4) -> 8472.72 | G5: =SUM(B5:F5) -> 43468.33
A6: East | B6: =SUMIFS(Dataset!$E$2:$E$201,Dataset!$C$2:$C$201,$A6,Dataset!$D$2:$D$201,B$4) -> 11389.09 | C6: =SUMIFS(Dataset!$E$2:$E$201,Dataset!$C$2:$C$201,$A6,Dataset!$D$2:$D$201,C$4) -> 2401.45 | D6: =SUMIFS(Dataset!$E$2:$E$201,Dataset!$C$2:$C$201,$A6,Dataset!$D$2:$D$201,D$4) -> 2869.54 | E6: =SUMIFS(Dataset!$E$2:$E$201,Dataset!$C$2:$C$201,$A6,Dataset!$D$2:$D$201,E$4) -> 7592.34 | F6: =SUMIFS(Dataset!$E$2:$E$201,Dataset!$C$2:$C$201,$A6,Dataset!$D$2:$D$201,F$4) -> 8189.22 | G6: =SUM(B6:F6) -> 32441.64
A7: North | B7: =SUMIFS(Dataset!$E$2:$E$201,Dataset!$C$2:$C$201,$A7,Dataset!$D$2:$D$201,B$4) -> 8037.01 | C7: =SUMIFS(Dataset!$E$2:$E$201,Dataset!$C$2:$C$201,$A7,Dataset!$D$2:$D$201,C$4) -> 8422.82 | D7: =SUMIFS(Dataset!$E$2:$E$201,Dataset!$C$2:$C$201,$A7,Dataset!$D$2:$D$201,D$4) -> 8191.71 | E7: =SUMIFS(Dataset!$E$2:$E$201,Dataset!$C$2:$C$201,$A7,Dataset!$D$2:$D$201,E$4) -> 6978.08 | F7: =SUMIFS(Dataset!$E$2:$E$201,Dataset!$C$2:$C$201,$A7,Dataset!$D$2:$D$201,F$4) -> 3345.8 | G7: =SUM(B7:F7) -> 34975.42
A8: South | B8: =SUMIFS(Dataset!$E$2:$E$201,Dataset!$C$2:$C$201,$A8,Dataset!$D$2:$D$201,B$4) -> 9588.04 | C8: =SUMIFS(Dataset!$E$2:$E$201,Dataset!$C$2:$C$201,$A8,Dataset!$D$2:$D$201,C$4) -> 8393.63 | D8: =SUMIFS(Dataset!$E$2:$E$201,Dataset!$C$2:$C$201,$A8,Dataset!$D$2:$D$201,D$4) -> 11989.07 | E8: =SUMIFS(Dataset!$E$2:$E$201,Dataset!$C$2:$C$201,$A8,Dataset!$D$2:$D$201,E$4) -> 7982.73 | F8: =SUMIFS(Dataset!$E$2:$E$201,Dataset!$C$2:$C$201,$A8,Dataset!$D$2:$D$201,F$4) -> 2295.32 | G8: =SUM(B8:F8) -> 40248.79
A9: West | B9: =SUMIFS(Dataset!$E$2:$E$201,Dataset!$C$2:$C$201,$A9,Dataset!$D$2:$D$201,B$4) -> 6691.17 | C9: =SUMIFS(Dataset!$E$2:$E$201,Dataset!$C$2:$C$201,$A9,Dataset!$D$2:$D$201,C$4) -> 10509.43 | D9: =SUMIFS(Dataset!$E$2:$E$201,Dataset!$C$2:$C$201,$A9,Dataset!$D$2:$D$201,D$4) -> 11372.44 | E9: =SUMIFS(Dataset!$E$2:$E$201,Dataset!$C$2:$C$201,$A9,Dataset!$D$2:$D$201,E$4) -> 9182.78 | F9: =SUMIFS(Dataset!$E$2:$E$201,Dataset!$C$2:$C$201,$A9,Dataset!$D$2:$D$201,F$4) -> 6327.76 | G9: =SUM(B9:F9) -> 44083.58
A10: Grand Total | B10: =SUM(B5:B9) -> 47002.46 | C10: =SUM(C5:C9) -> 41927.59 | D10: =SUM(D5:D9) -> 41044 | E10: =SUM(E5:E9) -> 36612.89 | F10: =SUM(F5:F9) -> 28630.82 | G10: =SUM(G5:G9) -> 195217.76
A12: Check vs Dataset | B12: =IF(ROUND(G10-SUM(Dataset!$E$2:$E$201),2)=0,"✔ ties","check") -> ✔ ties

Sheet Dashboard
A1: Sales Dashboard – PR. 2 Analyzer
A3: Total Sales | B3: Total Profit | C3: Profit Margin | D3: Orders | E3: Avg Discount
A4: =SUM(Dataset!$E$2:$E$201) -> 195217.76 | B4: =SUM(Dataset!$I$2:$I$201) -> 68287.01 | C4: =B4/A4 -> 0.34979917 | D4: =COUNTA(Dataset!$A$2:$A$201) -> 200 | E4: =AVERAGE(Dataset!$G$2:$G$201) -> 0.09725
A6: Key Insights
A7: ="Top region by sales: "&INDEX('Pivot Table'!A5:A9,MATCH(MAX('Pivot Table'!G5:G9),'Pivot Table'!G5:G9,0))&" (₹"&TEXT(MAX('Pivot Table'!G5:G9),"#,##0")&", "&TEXT(MAX('Pivot Table'!G5:G9)/'Pivot Table'!G10,"0.0%")&" of total)." -> Top region by sales: West (₹44,084, 22.6% of total).
A8: ="Top product category by sales: "&INDEX('Pivot Table'!B4:F4,MATCH(MAX('Pivot Table'!B10:F10),'Pivot Table'!B10:F10,0))&" (₹"&TEXT(MAX('Pivot Table'!B10:F10),"#,##0")&")." -> Top product category by sales: Books (₹47,002).
A9: ="Best month: "&TEXT(INDEX('Sales Growth'!A4:A16,MATCH(MAX('Sales Growth'!B4:B16),'Sales Growth'!B4:B16,0)),"mmm-yyyy")&" (₹"&TEXT(MAX('Sales Growth'!B4:B16),"#,##0")&"); weakest: "&TEXT(INDEX('Sales Growth'!A4:A16,MATCH(MIN('Sales Growth'!B4:B16),'Sales Growth'!B4:B16,0)),"mmm-yyyy")&" (₹"&TEXT(MIN('Sales Growth'!B4:B16),"#,##0")&")." -> Best month: Sep-2024 (₹20,534); weakest: Apr-2025 (₹3,212).
A10: ="Regression: Profit ≈ "&TEXT(Regression!B18,"0.00")&" + "&TEXT(Regression!B19,"0.000")&" × Sales (R² = "&TEXT(Regression!B6,"0.00")&")." -> Regression: Profit ≈ -1.03 + 0.351 × Sales (R² = 0.60).
A11: ="High-value customers (above-average total purchase): "&COUNTIF('High-Value Customers'!F6:F35,"High-Value")&" of 30; the top 10 account for "&TEXT(SUMIF('Top 10 Customers'!C4:C33,"<=10",'Top 10 Customers'!B4:B33)/A4,"0.0%")&" of sales." -> High-value customers (above-average total purchase): 15 of 30; the top 10 account for 47.3% of sales.
A12: ="What-if: moving the discount to "&TEXT('What-If Analysis'!B8,"0%")&" changes total profit by "&TEXT('What-If Analysis'!B11,"₹#,##0;-₹#,##0")&" ("&TEXT('What-If Analysis'!B12,"0.0%;-0.0%")&")." -> What-if: moving the discount to 10% changes total profit by ₹1,007 (1.5%).
